CHANGE_LOG
LICENCE
MANIFEST.in
README.md
paster.cfg
pstr
setup.py
paster/__init__.py
paster/config.py
paster/parser.py
paster/services.py
paster.egg-info/PKG-INFO
paster.egg-info/SOURCES.txt
paster.egg-info/dependency_links.txt
paster.egg-info/top_level.txt