Metadata-Version: 1.0
Name: paster
Version: 0.7
Summary: A generic pastebin posting tool
Home-page: https://github.com/crodjer/paster
Author: Rohan Jain
Author-email: crodjer@gmail.com
License: GPLv3
Platform: all
Classifier: Development Status :: 4 - Beta
Classifier: Environment :: Console
Classifier: License :: OSI Approved :: GNU General Public License (GPL)
Classifier: Natural Language :: English
Classifier: Intended Audience :: End Users/Desktop
Classifier: Intended Audience :: Developers
Classifier: Intended Audience :: System Administrators
Classifier: Topic :: Software Development
Classifier: Programming Language :: Python
Classifier: Natural Language :: English
